apollolib/__init__.py
apollolib/apollo_client.py
apollolib/feature_switch.py
apollolib/open_setting.py
featurepalette/__init__.py
featurepalette/featurepalette_client.py
featurepalette/errno/__init__.py
featurepalette/errno/constants.py
featurepalette/errno/ttypes.py
featurepalette/response/__init__.py
featurepalette/response/constants.py
featurepalette/response/ttypes.py
featurepalette/service/FeaturePalette.py
featurepalette/service/__init__.py
featurepalette/service/constants.py
featurepalette/service/ttypes.py
featurepalette/trace/__init__.py
featurepalette/trace/constants.py
featurepalette/trace/ttypes.py
util/__init__.py
util/log.py
util/metric.py
util/path.py
util/service.py
util/time.py
dengine_util_py-3.0.8.dist-info/METADATA
dengine_util_py-3.0.8.dist-info/WHEEL
dengine_util_py-3.0.8.dist-info/top_level.txt
dengine_util_py-3.0.8.dist-info/RECORD
