Metadata-Version: 2.1
Name: dengine-util-py
Version: 3.0.8
Summary: clients that encompass configuration and feature services, with built-in logging and metrics reporting capabilities.
Home-page: UNKNOWN
Author: zhangmanni
Author-email: zhangmanni@didiglobal.com
License: UNKNOWN
Platform: UNKNOWN
Classifier: Programming Language :: Python :: 3
Classifier: License :: OSI Approved :: MIT License
Classifier: Operating System :: OS Independent
